LICENSE
MANIFEST.in
README.md
setup.py
/Users/rdm/Codes/todoist-tracker/bin/todoist-tracker
bin/todoist-tracker
requirements/python
requirements/python-dev
todoist_tracker/__init__.py
todoist_tracker/overdue.py
todoist_tracker.egg-info/PKG-INFO
todoist_tracker.egg-info/SOURCES.txt
todoist_tracker.egg-info/dependency_links.txt
todoist_tracker.egg-info/not-zip-safe
todoist_tracker.egg-info/requires.txt
todoist_tracker.egg-info/top_level.txt
todoist_tracker/cli/__init__.py
todoist_tracker/cli/base.py
todoist_tracker/cli/utils.py
todoist_tracker/cli/overdue/__init__.py
todoist_tracker/cli/overdue/n.py
todoist_tracker/cli/overdue/priority.py
todoist_tracker/cli/overdue/time.py