Metadata-Version: 1.1
Name: todoist-tracker
Version: 0.1.3
Summary: track various metrics for todoist
Home-page: https://github.com/deanmalmgren/todoist-tracker
Author: Dean Malmgren
Author-email: dean.malmgren@datascopeanalytics.com
License: MIT
Download-URL: https://github.com/deanmalmgren/todoist-tracker/archives/master
Platform: UNKNOWN
